tapo-0.8.6.dist-info/METADATA
tapo-0.8.6.dist-info/WHEEL
tapo-0.8.6.dist-info/licenses/LICENSE
tapo.libs/libgcc_s-39080030.so.1
tapo/__init__.py
tapo/__init__.pyi
tapo/api_client.pyi
tapo/color_light_handler.pyi
tapo/device_discovery.pyi
tapo/discovery_result.pyi
tapo/generic_device_handler.pyi
tapo/hub_handler.pyi
tapo/ke100_handler.pyi
tapo/light_handler.pyi
tapo/plug_energy_monitoring_handler.pyi
tapo/plug_handler.pyi
tapo/power_strip_energy_monitoring_handler.pyi
tapo/power_strip_handler.pyi
tapo/power_strip_plug_energy_monitoring_handler.pyi
tapo/power_strip_plug_handler.pyi
tapo/requests/__init__.py
tapo/requests/__init__.pyi
tapo/requests/energy_data_interval.pyi
tapo/requests/play_alarm.pyi
tapo/requests/power_data_interval.pyi
tapo/requests/set_device_info/__init__.py
tapo/requests/set_device_info/__init__.pyi
tapo/requests/set_device_info/color.pyi
tapo/requests/set_device_info/color_light.pyi
tapo/requests/set_device_info/lighting_effect.pyi
tapo/responses/__init__.py
tapo/responses/__init__.pyi
tapo/responses/child_device_list_hub_result/__init__.py
tapo/responses/child_device_list_hub_result/__init__.pyi
tapo/responses/child_device_list_hub_result/hub_result.pyi
tapo/responses/child_device_list_hub_result/ke100_result.pyi
tapo/responses/child_device_list_hub_result/s200b_result.pyi
tapo/responses/child_device_list_hub_result/status.pyi
tapo/responses/child_device_list_hub_result/t100_result.pyi
tapo/responses/child_device_list_hub_result/t110_result.pyi
tapo/responses/child_device_list_hub_result/t300_result.pyi
tapo/responses/child_device_list_hub_result/t31x_result.pyi
tapo/responses/child_device_list_hub_result/temperature_unit.pyi
tapo/responses/child_device_list_power_strip_result/__init__.py
tapo/responses/child_device_list_power_strip_result/__init__.pyi
tapo/responses/child_device_list_power_strip_result/power_strip_plug_energy_monitoring_result.pyi
tapo/responses/child_device_list_power_strip_result/power_strip_plug_result.pyi
tapo/responses/current_power_result.pyi
tapo/responses/device_info_result/__init__.py
tapo-0.8.6.dist-info/RECORD
