Metadata-Version: 2.4
Name: tapo
Version: 0.8.6
Classifier: Development Status :: 4 - Beta
Classifier: Topic :: Software Development :: Embedded Systems
Classifier: Environment :: Console
Classifier: Operating System :: OS Independent
Classifier: License :: OSI Approved :: MIT License
Classifier: Intended Audience :: Developers
Classifier: Topic :: Home Automation
Classifier: Programming Language :: Python :: 3.9
Classifier: Programming Language :: Python :: 3.10
Classifier: Programming Language :: Python :: 3.11
Classifier: Programming Language :: Python :: 3.12
Classifier: Programming Language :: Python :: 3.13
License-File: LICENSE
Summary: Unofficial Tapo API Client. Works with TP-Link Tapo smart devices. Tested with light bulbs (L510, L520, L530, L535, L610, L630), light strips (L900, L920, L930), plugs (P100, P105, P110, P110M, P115), power strips (P300, P304M, P306, P316M), hubs (H100), switches (S200B) and sensors (KE100, T100, T110, T300, T310, T315).
Keywords: Tapo,TP-Link,Smart Home,Home Automation,IoT
Author-email: Mihai Dinculescu <mihai.dinculescu@outlook.com>
Maintainer-email: Mihai Dinculescu <mihai.dinculescu@outlook.com>
Requires-Python: >=3.9
Project-URL: Changelog, https://github.com/mihai-dinculescu/tapo/blob/main/CHANGELOG.md
Project-URL: Funding, https://github.com/mihai-dinculescu
Project-URL: Homepage, https://github.com/mihai-dinculescu/tapo
Project-URL: Source, https://github.com/mihai-dinculescu/tapo
